{
    "key": "alexscaves_radrock",
    "category": "stone",
    "primary": 4.5,
    "secondary": 5,
    "tertiary": 0,
    "durability": 512,
    "integrityCost": 3,
    "integrityGain": 1,
    "magicCapacity": 108,
    "toolLevel": "minecraft:iron",
    "toolEfficiency": 9,
    "effects": {
        "fierySelf": [
            3,
            0.06
        ]
    },
    "tints": {
        "glyph": "2f3c22",
        "texture": "2f3c22"
    },
    "textures": [
        "grainy",
        "crude",
        "default"
    ],
    "material": {
        "items": [
            "alexscaves:radrock"
        ]
    },
    "requiredTools": {
        "hammer_dig": "minecraft:stone"
    },
    "conditions": [
        {
            "type": "forge:mod_loaded",
            "modid": "alexscaves"
        }
    ]
}