{
    "key": "unearthed_dolerite",
    "category": "stone",
    "primary": 4.2,
    "secondary": 3.8,
    "tertiary": 0,
    "durability": 192,
    "integrityCost": 2,
    "integrityGain": 3,
    "magicCapacity": 90,
    "toolLevel": "minecraft:stone",
    "toolEfficiency": 4.5,
    "tints": {
        "glyph": "6C6965",
        "texture": "6C6965"
    },
    "textures": [
        "grainy",
        "crude",
        "default"
    ],
    "material": {
        "items": [
            "unearthed:dolerite"
        ]
    },
    "requiredTools": {
        "hammer_dig": "minecraft:wood"
    },
    "conditions": [
        {
            "type": "forge:mod_loaded",
            "modid": "unearthed"
        }
    ]
}