{
    "key": "ms_olivine",
    "category": "gem",
    "primary": "4.6",
    "secondary": "2.9",
    "tertiary": "0",
    "durability": "228",
    "integrityCost": "2",
    "integrityGain": "2",
    "magicCapacity": "60",
    "toolLevel": "2",
    "toolEfficiency": "5",
    "tints": {
        "glyph": "5aff4f",
        "texture": "5aff4f"
    },
    "textures": [
        "shiny",
        "crude"
    ],
    "material": {
        "item": "ms:gem/olivine"
    },
    "requiredTools": {
        "hammer_dig": "minecraft:stone"
    },
    "conditions": [
        {
            "type": "forge:mod_loaded",
            "modid": "ms"
        }
    ]
}